asimov_near_module/__init__.py
asimov_near_module/fetcher/__init__.py
asimov_near_module/fetcher/__main__.py
asimov_near_module/fetcher/asimov-near-fetcher
asimov_near_module-0.0.1.dist-info/entry_points.txt
asimov_near_module-0.0.1.dist-info/METADATA
asimov_near_module-0.0.1.dist-info/WHEEL
asimov_near_module-0.0.1.dist-info/RECORD
