Metadata-Version: 2.1
Name: asimov-near-module
Version: 0.0.1
Summary: ASIMOV module for data import from the NEAR Protocol blockchain network.
Author-email: ASIMOV Protocol <support@asimov.so>
Project-URL: Homepage, https://github.com/asimov-modules
Project-URL: Repository, https://github.com/asimov-modules/asimov-near-module
Project-URL: Changelog, https://github.com/asimov-modules/asimov-near-module/blob/master/CHANGES.md
Project-URL: Download, https://github.com/asimov-modules/asimov-near-module/releases/tag/0.0.1
Project-URL: Releases, https://github.com/asimov-modules/asimov-near-module/releases
Project-URL: Issues, https://github.com/asimov-modules/asimov-near-module/issues
Project-URL: Documentation, https://github.com/asimov-modules/asimov-near-module/blob/master/README.md
Keywords: asimov-module,asimov,ai
Classifier: Development Status :: 4 - Beta
Classifier: Environment :: Console
Classifier: Intended Audience :: Developers
Classifier: Intended Audience :: System Administrators
Classifier: Programming Language :: Python :: 3
Classifier: Programming Language :: Rust
Classifier: Topic :: Scientific/Engineering :: Artificial Intelligence
Classifier: Topic :: Software Development :: Libraries
Classifier: Topic :: Text Processing :: General
License: Unlicense
